zeroish/__init__.py
zeroish/zeroish.py
zeroish-0.0.2.dist-info/METADATA
zeroish-0.0.2.dist-info/WHEEL
zeroish-0.0.2.dist-info/entry_points.txt
zeroish-0.0.2.dist-info/top_level.txt
zeroish-0.0.2.dist-info/RECORD
