Metadata-Version: 2.1
Name: zeroish
Version: 0.0.2
Summary: Provide a probability of false negatives for compositional count-based data
Author-email: Jonathan Golob <j-dev@golob.org>
Project-URL: Homepage, https://github.com/jgolob/zeroish
Project-URL: Issues, https://github.com/jgolob/zeroish/issues
Classifier: Programming Language :: Python :: 3
Classifier: License :: OSI Approved :: MIT License
Classifier: Operating System :: OS Independent
Requires-Python: >=3.8
Requires-Dist: numpy
Requires-Dist: pandas
Requires-Dist: anndata
Requires-Dist: scipy
Requires-Dist: numba
